nomenclature_sdk/__init__.py
nomenclature_sdk/__init__.pyi
nomenclature_sdk/_internal.cpython-310-x86_64-linux-gnu.so
nomenclature_sdk/_internal.pyi
nomenclature_sdk/client.cpython-310-x86_64-linux-gnu.so
nomenclature_sdk/client.pyi
nomenclature_sdk/connection.cpython-310-x86_64-linux-gnu.so
nomenclature_sdk/connection.pyi
nomenclature_sdk/errors.py
nomenclature_sdk/errors.pyi
nomenclature_sdk/models.py
nomenclature_sdk/models.pyi
nomenclature_sdk/py.typed
tests/__init__.py
nomenclature_sdk-1.0.7.dist-info/METADATA
nomenclature_sdk-1.0.7.dist-info/WHEEL
nomenclature_sdk-1.0.7.dist-info/top_level.txt
nomenclature_sdk-1.0.7.dist-info/RECORD
