Metadata-Version: 2.4
Name: nomenclature_sdk
Version: 1.0.7
Requires-Dist: pyodbc
Dynamic: description
Dynamic: description-content-type
Dynamic: requires-dist
